README.txt
setup.py
sikwan/__init__.py
sikwan.spfcheck.egg-info/PKG-INFO
sikwan.spfcheck.egg-info/SOURCES.txt
sikwan.spfcheck.egg-info/dependency_links.txt
sikwan.spfcheck.egg-info/namespace_packages.txt
sikwan.spfcheck.egg-info/requires.txt
sikwan.spfcheck.egg-info/top_level.txt
sikwan/spfcheck/__init__.py