Metadata-Version: 1.0
Name: sikwan.spfcheck
Version: 0.1.6dev
Summary: A package to check SPF status
Home-page: https://github.com/Sikwan/spfcheck
Author: Francois Vanderkelen
Author-email: vanderkelen.francois@gmail.com
License: GPL
Keywords: sikwan spf spfcheck
Platform: UNKNOWN
Classifier: Development Status :: 3 - Alpha
Classifier: Intended Audience :: Developers
Classifier: Intended Audience :: System Administrators
Classifier: License :: OSI Approved :: GNU General Public License (GPL)
Classifier: Operating System :: Unix
Classifier: Programming Language :: Python
Classifier: Topic :: Software Development :: Libraries :: Python Modules
